leftweeks/__init__.py
leftweeks/cli.py
leftweeks/plot.py
leftweeks/utils.py
leftweeks-0.1.0.dist-info/METADATA
leftweeks-0.1.0.dist-info/WHEEL
leftweeks-0.1.0.dist-info/entry_points.txt
leftweeks-0.1.0.dist-info/RECORD
