Metadata-Version: 2.4
Name: leftweeks
Version: 0.1.0
Summary: Add your description here
Requires-Python: >=3.12
Requires-Dist: click>=8.1.8
Requires-Dist: matplotlib>=3.10.1
